lipsutils/__init__.py
lipsutils/fmt_io.py
lipsutils/ionic_info.py
lipsutils/ionic_launch.py
lipsutils/log_utils.py
lipsutils/profiling.py
lipsutils-0.0.3.dist-info/METADATA
lipsutils-0.0.3.dist-info/WHEEL
lipsutils-0.0.3.dist-info/licenses/LICENSE
lipsutils-0.0.3.dist-info/RECORD
